[{"expand": "operations,versionedRepresentations,editmeta,changelog,customfield_10010.requestTypePractice,renderedFields", "id": "17450", "self": "https://ganaz.atlassian.net/rest/api/2/issue/17450", "key": "GAN-5841", "changelog": {"startAt": 0, "maxResults": 6, "total": 6, "histories": [{"id": "81842", "author": {"self": "https://ganaz.atlassian.net/rest/api/2/user?accountId=613e6eaa1238e8007108f513", "accountId": "613e6eaa1238e8007108f513", "emailAddress": "kjell@ganaz.com", "avatarUrls": {"48x48": "https://secure.gravatar.com/avatar/339f4dbb6014520e051050dc4711fbc9?d=https%3A%2F%2Favatar-management--avatars.us-west-2.prod.public.atl-paas.net%2Finitials%2FKH-0.png", "24x24": "https://secure.gravatar.com/avatar/339f4dbb6014520e051050dc4711fbc9?d=https%3A%2F%2Favatar-management--avatars.us-west-2.prod.public.atl-paas.net%2Finitials%2FKH-0.png", "16x16": "https://secure.gravatar.com/avatar/339f4dbb6014520e051050dc4711fbc9?d=https%3A%2F%2Favatar-management--avatars.us-west-2.prod.public.atl-paas.net%2Finitials%2FKH-0.png", "32x32": "https://secure.gravatar.com/avatar/339f4dbb6014520e051050dc4711fbc9?d=https%3A%2F%2Favatar-management--avatars.us-west-2.prod.public.atl-paas.net%2Finitials%2FKH-0.png"}, "displayName": "Kjell Hedstrom", "active": true, "timeZone": "US/Mountain", "accountType": "atlassian"}, "created": "2023-06-06T11:40:32.582-0700", "items": [{"field": "resolution", "fieldtype": "jira", "fieldId": "resolution", "from": null, "fromString": null, "to": "10000", "toString": "Done"}, {"field": "status", "fieldtype": "jira", "fieldId": "status", "from": "10103", "fromString": "In Review", "to": "6", "toString": "Closed"}]}, {"id": "81756", "author": {"self": "https://ganaz.atlassian.net/rest/api/2/user?accountId=613e6eaa1238e8007108f513", "accountId": "613e6eaa1238e8007108f513", "emailAddress": "kjell@ganaz.com", "avatarUrls": {"48x48": "https://secure.gravatar.com/avatar/339f4dbb6014520e051050dc4711fbc9?d=https%3A%2F%2Favatar-management--avatars.us-west-2.prod.public.atl-paas.net%2Finitials%2FKH-0.png", "24x24": "https://secure.gravatar.com/avatar/339f4dbb6014520e051050dc4711fbc9?d=https%3A%2F%2Favatar-management--avatars.us-west-2.prod.public.atl-paas.net%2Finitials%2FKH-0.png", "16x16": "https://secure.gravatar.com/avatar/339f4dbb6014520e051050dc4711fbc9?d=https%3A%2F%2Favatar-management--avatars.us-west-2.prod.public.atl-paas.net%2Finitials%2FKH-0.png", "32x32": "https://secure.gravatar.com/avatar/339f4dbb6014520e051050dc4711fbc9?d=https%3A%2F%2Favatar-management--avatars.us-west-2.prod.public.atl-paas.net%2Finitials%2FKH-0.png"}, "displayName": "Kjell Hedstrom", "active": true, "timeZone": "US/Mountain", "accountType": "atlassian"}, "created": "2023-06-05T08:58:08.945-0700", "items": [{"field": "labels", "fieldtype": "jira", "fieldId": "labels", "from": null, "fromString": "", "to": null, "toString": "xops_packet_update"}]}, {"id": "81615", "author": {"self": "https://ganaz.atlassian.net/rest/api/2/user?accountId=62780ad493111000689ece08", "accountId": "62780ad493111000689ece08", "emailAddress": "daniel.s@ganaz.com", "avatarUrls": {"48x48": "https://secure.gravatar.com/avatar/6c67edf746841016d29f333698b7f211?d=https%3A%2F%2Favatar-management--avatars.us-west-2.prod.public.atl-paas.net%2Finitials%2FDS-5.png", "24x24": "https://secure.gravatar.com/avatar/6c67edf746841016d29f333698b7f211?d=https%3A%2F%2Favatar-management--avatars.us-west-2.prod.public.atl-paas.net%2Finitials%2FDS-5.png", "16x16": "https://secure.gravatar.com/avatar/6c67edf746841016d29f333698b7f211?d=https%3A%2F%2Favatar-management--avatars.us-west-2.prod.public.atl-paas.net%2Finitials%2FDS-5.png", "32x32": "https://secure.gravatar.com/avatar/6c67edf746841016d29f333698b7f211?d=https%3A%2F%2Favatar-management--avatars.us-west-2.prod.public.atl-paas.net%2Finitials%2FDS-5.png"}, "displayName": "Daniel Schatz-Miller", "active": true, "timeZone": "America/Los_Angeles", "accountType": "atlassian"}, "created": "2023-06-02T06:57:29.970-0700", "items": [{"field": "status", "fieldtype": "jira", "fieldId": "status", "from": "3", "fromString": "In Progress", "to": "10103", "toString": "In Review"}]}, {"id": "81614", "author": {"self": "https://ganaz.atlassian.net/rest/api/2/user?accountId=62780ad493111000689ece08", "accountId": "62780ad493111000689ece08", "emailAddress": "daniel.s@ganaz.com", "avatarUrls": {"48x48": "https://secure.gravatar.com/avatar/6c67edf746841016d29f333698b7f211?d=https%3A%2F%2Favatar-management--avatars.us-west-2.prod.public.atl-paas.net%2Finitials%2FDS-5.png", "24x24": "https://secure.gravatar.com/avatar/6c67edf746841016d29f333698b7f211?d=https%3A%2F%2Favatar-management--avatars.us-west-2.prod.public.atl-paas.net%2Finitials%2FDS-5.png", "16x16": "https://secure.gravatar.com/avatar/6c67edf746841016d29f333698b7f211?d=https%3A%2F%2Favatar-management--avatars.us-west-2.prod.public.atl-paas.net%2Finitials%2FDS-5.png", "32x32": "https://secure.gravatar.com/avatar/6c67edf746841016d29f333698b7f211?d=https%3A%2F%2Favatar-management--avatars.us-west-2.prod.public.atl-paas.net%2Finitials%2FDS-5.png"}, "displayName": "Daniel Schatz-Miller", "active": true, "timeZone": "America/Los_Angeles", "accountType": "atlassian"}, "created": "2023-06-02T06:48:28.830-0700", "items": [{"field": "status", "fieldtype": "jira", "fieldId": "status", "from": "10101", "fromString": "To Do", "to": "3", "toString": "In Progress"}]}, {"id": "81613", "author": {"self": "https://ganaz.atlassian.net/rest/api/2/user?accountId=62780ad493111000689ece08", "accountId": "62780ad493111000689ece08", "emailAddress": "daniel.s@ganaz.com", "avatarUrls": {"48x48": "https://secure.gravatar.com/avatar/6c67edf746841016d29f333698b7f211?d=https%3A%2F%2Favatar-management--avatars.us-west-2.prod.public.atl-paas.net%2Finitials%2FDS-5.png", "24x24": "https://secure.gravatar.com/avatar/6c67edf746841016d29f333698b7f211?d=https%3A%2F%2Favatar-management--avatars.us-west-2.prod.public.atl-paas.net%2Finitials%2FDS-5.png", "16x16": "https://secure.gravatar.com/avatar/6c67edf746841016d29f333698b7f211?d=https%3A%2F%2Favatar-management--avatars.us-west-2.prod.public.atl-paas.net%2Finitials%2FDS-5.png", "32x32": "https://secure.gravatar.com/avatar/6c67edf746841016d29f333698b7f211?d=https%3A%2F%2Favatar-management--avatars.us-west-2.prod.public.atl-paas.net%2Finitials%2FDS-5.png"}, "displayName": "Daniel Schatz-Miller", "active": true, "timeZone": "America/Los_Angeles", "accountType": "atlassian"}, "created": "2023-06-02T06:48:27.137-0700", "items": [{"field": "assignee", "fieldtype": "jira", "fieldId": "assignee", "from": null, "fromString": null, "to": "62780ad493111000689ece08", "toString": "Daniel Schatz-Miller", "tmpFromAccountId": null, "tmpToAccountId": "62780ad493111000689ece08"}]}, {"id": "81597", "author": {"self": "https://ganaz.atlassian.net/rest/api/2/user?accountId=618067a4b9c549006f45c3ac", "accountId": "618067a4b9c549006f45c3ac", "emailAddress": "edgar.cc@ganaz.com", "avatarUrls": {"48x48": "https://avatar-management--avatars.us-west-2.prod.public.atl-paas.net/618067a4b9c549006f45c3ac/70741788-e907-474c-b0d1-f4a612d64569/48", "24x24": "https://avatar-management--avatars.us-west-2.prod.public.atl-paas.net/618067a4b9c549006f45c3ac/70741788-e907-474c-b0d1-f4a612d64569/24", "16x16": "https://avatar-management--avatars.us-west-2.prod.public.atl-paas.net/618067a4b9c549006f45c3ac/70741788-e907-474c-b0d1-f4a612d64569/16", "32x32": "https://avatar-management--avatars.us-west-2.prod.public.atl-paas.net/618067a4b9c549006f45c3ac/70741788-e907-474c-b0d1-f4a612d64569/32"}, "displayName": "Edgar Cholewa-Cardona", "active": true, "timeZone": "America/Los_Angeles", "accountType": "atlassian"}, "created": "2023-06-01T18:14:22.054-0700", "items": [{"field": "description", "fieldtype": "jira", "fieldId": "description", "from": null, "fromString": "_Context_: this packet will be used to fix some information problems that occurred on the I9 belonging to this customer. \n\n{panel:bgColor=#deebff}\nHere is the link to [slack|https://ganazhq.slack.com/archives/C022BDETJQ1/p1684352468886879] for more context\n{panel}\n\n* Language: *Espa\u00f1ol*\n* *Packet Name*: I9 Only - Scurich\n* *Packet type*: I9\n** ANVIL Packet:\n*** I9 Standalone - Scurich: [https://app.useanvil.com/org/ganaz/w/i9-standalone-scurich/edit/preview?web=2CPGcZQKIRQg3JVhxqzq&doc=3e7c53c0-3335-11ea-92e1-f5f0e11b5e89|https://app.useanvil.com/org/ganaz/w/i9-standalone-scurich/edit/preview?web=2CPGcZQKIRQg3JVhxqzq&doc=3e7c53c0-3335-11ea-92e1-f5f0e11b5e89|smart-link] \n*** {color:#ff5630}*Allocate this packets at the bottom of the list*{color}\u00a0\n\n{panel:bgColor=#deebff}\nLink to similar [Ticket|https://ganaz.atlassian.net/browse/GAN-5462?atlOrigin=eyJpIjoiOGZiODA0ODY1ZjQ3NDdmM2E4Y2JiNzYwMzMyMjBjZmUiLCJwIjoiaiJ9] (i9 Standalone)\n{panel}\n\n\n\nIf you have questions, please reach me.", "to": null, "toString": "_Context_: this packet will be used to fix some information problems that occurred on the I9 belonging to this customer. \n\n{panel:bgColor=#deebff}\nHere is the link to [slack|https://ganazhq.slack.com/archives/C022BDETJQ1/p1684352468886879] for more context\n{panel}\n\n* Language: *Espa\u00f1ol*\n* *Packet Name*: Doc Correction Scurich 3/29/23 - 5/17/23\n* *Packet type*: I9\n** ANVIL Packet:\n*** I9 Standalone - Scurich: [https://app.useanvil.com/org/ganaz/w/i9-standalone-scurich/edit/preview?web=2CPGcZQKIRQg3JVhxqzq&doc=3e7c53c0-3335-11ea-92e1-f5f0e11b5e89|https://app.useanvil.com/org/ganaz/w/i9-standalone-scurich/edit/preview?web=2CPGcZQKIRQg3JVhxqzq&doc=3e7c53c0-3335-11ea-92e1-f5f0e11b5e89|smart-link] \n*** {color:#ff5630}*Allocate this packets at the bottom of the list*{color}\u00a0\n\n{panel:bgColor=#deebff}\nLink to similar [Ticket|https://ganaz.atlassian.net/browse/GAN-5462?atlOrigin=eyJpIjoiOGZiODA0ODY1ZjQ3NDdmM2E4Y2JiNzYwMzMyMjBjZmUiLCJwIjoiaiJ9] (i9 Standalone)\n{panel}\n\n\n\nIf you have questions, please reach me."}]}]}, "fields": {"statuscategorychangedate": "2023-06-06T11:40:32.561-0700", "fixVersions": [], "resolution": {"self": "https://ganaz.atlassian.net/rest/api/2/resolution/10000", "id": "10000", "description": "Work has been completed on this issue.", "name": "Done"}, "customfield_10105": null, "customfield_10109": null, "lastViewed": null, "priority": {"self": "https://ganaz.atlassian.net/rest/api/2/priority/3", "iconUrl": "https://ganaz.atlassian.net/images/icons/priorities/medium.svg", "name": "Medium", "id": "3"}, "customfield_10101": null, "customfield_10103": null, "labels": ["xops_packet_update"], "aggregatetimeoriginalestimate": null, "timeestimate": null, "versions": [], "issuelinks": [], "assignee": {"self": "https://ganaz.atlassian.net/rest/api/2/user?accountId=62780ad493111000689ece08", "accountId": "62780ad493111000689ece08", "emailAddress": "daniel.s@ganaz.com", "avatarUrls": {"48x48": "https://secure.gravatar.com/avatar/6c67edf746841016d29f333698b7f211?d=https%3A%2F%2Favatar-management--avatars.us-west-2.prod.public.atl-paas.net%2Finitials%2FDS-5.png", "24x24": "https://secure.gravatar.com/avatar/6c67edf746841016d29f333698b7f211?d=https%3A%2F%2Favatar-management--avatars.us-west-2.prod.public.atl-paas.net%2Finitials%2FDS-5.png", "16x16": "https://secure.gravatar.com/avatar/6c67edf746841016d29f333698b7f211?d=https%3A%2F%2Favatar-management--avatars.us-west-2.prod.public.atl-paas.net%2Finitials%2FDS-5.png", "32x32": "https://secure.gravatar.com/avatar/6c67edf746841016d29f333698b7f211?d=https%3A%2F%2Favatar-management--avatars.us-west-2.prod.public.atl-paas.net%2Finitials%2FDS-5.png"}, "displayName": "Daniel Schatz-Miller", "active": true, "timeZone": "America/Los_Angeles", "accountType": "atlassian"}, "status": {"self": "https://ganaz.atlassian.net/rest/api/2/status/6", "description": "The issue is considered finished, the resolution is correct. Issues which are closed can be reopened.", "iconUrl": "https://ganaz.atlassian.net/images/icons/statuses/closed.png", "name": "Closed", "id": "6", "statusCategory": {"self": "https://ganaz.atlassian.net/rest/api/2/statuscategory/3", "id": 3, "key": "done", "colorName": "green", "name": "Done"}}, "components": [], "aggregatetimeestimate": null, "creator": {"self": "https://ganaz.atlassian.net/rest/api/2/user?accountId=618d80f4abad3c0071fae24e", "accountId": "618d80f4abad3c0071fae24e", "emailAddress": "osmar.e@ganaz.com", "avatarUrls": {"48x48": "https://avatar-management--avatars.us-west-2.prod.public.atl-paas.net/618d80f4abad3c0071fae24e/bc69d2f8-4938-4a4e-8407-84feff5db86f/48", "24x24": "https://avatar-management--avatars.us-west-2.prod.public.atl-paas.net/618d80f4abad3c0071fae24e/bc69d2f8-4938-4a4e-8407-84feff5db86f/24", "16x16": "https://avatar-management--avatars.us-west-2.prod.public.atl-paas.net/618d80f4abad3c0071fae24e/bc69d2f8-4938-4a4e-8407-84feff5db86f/16", "32x32": "https://avatar-management--avatars.us-west-2.prod.public.atl-paas.net/618d80f4abad3c0071fae24e/bc69d2f8-4938-4a4e-8407-84feff5db86f/32"}, "displayName": "Osmar Especiano Jimenez", "active": true, "timeZone": "America/Los_Angeles", "accountType": "atlassian"}, "subtasks": [], "customfield_10160": null, "customfield_10161": null, "customfield_10162": null, "reporter": {"self": "https://ganaz.atlassian.net/rest/api/2/user?accountId=618d80f4abad3c0071fae24e", "accountId": "618d80f4abad3c0071fae24e", "emailAddress": "osmar.e@ganaz.com", "avatarUrls": {"48x48": "https://avatar-management--avatars.us-west-2.prod.public.atl-paas.net/618d80f4abad3c0071fae24e/bc69d2f8-4938-4a4e-8407-84feff5db86f/48", "24x24": "https://avatar-management--avatars.us-west-2.prod.public.atl-paas.net/618d80f4abad3c0071fae24e/bc69d2f8-4938-4a4e-8407-84feff5db86f/24", "16x16": "https://avatar-management--avatars.us-west-2.prod.public.atl-paas.net/618d80f4abad3c0071fae24e/bc69d2f8-4938-4a4e-8407-84feff5db86f/16", "32x32": "https://avatar-management--avatars.us-west-2.prod.public.atl-paas.net/618d80f4abad3c0071fae24e/bc69d2f8-4938-4a4e-8407-84feff5db86f/32"}, "displayName": "Osmar Especiano Jimenez", "active": true, "timeZone": "America/Los_Angeles", "accountType": "atlassian"}, "aggregateprogress": {"progress": 0, "total": 0}, "customfield_10159": null, "progress": {"progress": 0, "total": 0}, "votes": {"self": "https://ganaz.atlassian.net/rest/api/2/issue/GAN-5841/votes", "votes": 0, "hasVoted": false}, "worklog": {"startAt": 0, "maxResults": 20, "total": 0, "worklogs": []}, "issuetype": {"self": "https://ganaz.atlassian.net/rest/api/2/issuetype/10104", "id": "10104", "description": "", "iconUrl": "https://ganaz.atlassian.net/rest/api/2/universal_avatar/view/type/issuetype/avatar/10320?size=medium", "name": "Support Request", "subtask": false, "avatarId": 10320, "hierarchyLevel": 0}, "timespent": null, "customfield_10150": null, "customfield_10151": [], "customfield_10152": null, "project": {"self": "https://ganaz.atlassian.net/rest/api/2/project/10100", "id": "10100", "key": "GAN", "name": "Ganaz", "projectTypeKey": "software", "simplified": false, "avatarUrls": {"48x48": "https://ganaz.atlassian.net/rest/api/2/universal_avatar/view/type/project/avatar/10412", "24x24": "https://ganaz.atlassian.net/rest/api/2/universal_avatar/view/type/project/avatar/10412?size=small", "16x16": "https://ganaz.atlassian.net/rest/api/2/universal_avatar/view/type/project/avatar/10412?size=xsmall", "32x32": "https://ganaz.atlassian.net/rest/api/2/universal_avatar/view/type/project/avatar/10412?size=medium"}}, "customfield_10153": null, "customfield_10154": null, "aggregatetimespent": null, "customfield_10155": null, "customfield_10156": null, "customfield_10157": null, "customfield_10158": null, "customfield_10148": null, "customfield_10149": null, "customfield_10028": null, "resolutiondate": "2023-06-06T11:40:32.544-0700", "workratio": -1, "watches": {"self": "https://ganaz.atlassian.net/rest/api/2/issue/GAN-5841/watchers", "watchCount": 3, "isWatching": true}, "issuerestriction": {"issuerestrictions": {}, "shouldDisplay": false}, "created": "2023-06-01T17:02:36.668-0700", "customfield_10140": null, "customfield_10141": null, "customfield_10020": null, "customfield_10142": null, "customfield_10021": null, "customfield_10143": null, "customfield_10022": null, "customfield_10144": null, "customfield_10023": null, "customfield_10145": null, "customfield_10024": "2023-06-02T06:57:43.693-0700", "customfield_10025": "3_*:*_1_*:*_541140_*|*_6_*:*_1_*:*_0_*|*_10101_*:*_1_*:*_49552162_*|*_10103_*:*_1_*:*_362582612", "customfield_10146": null, "customfield_10147": null, "customfield_10016": null, "customfield_10137": null, "customfield_10138": null, "customfield_10017": null, "customfield_10139": null, "customfield_10018": {"hasEpicLinkFieldDependency": false, "showField": false, "nonEditableReason": {"reason": "PLUGIN_LICENSE_ERROR", "message": "The Parent Link is only available to Jira Premium users."}}, "customfield_10019": "0|i017bb:", "updated": "2023-06-06T11:40:32.561-0700", "timeoriginalestimate": null, "description": "_Context_: this packet will be used to fix some information problems that occurred on the I9 belonging to this customer. \n\n{panel:bgColor=#deebff}\nHere is the link to [slack|https://ganazhq.slack.com/archives/C022BDETJQ1/p1684352468886879] for more context\n{panel}\n\n* Language: *Espa\u00f1ol*\n* *Packet Name*: Doc Correction Scurich 3/29/23 - 5/17/23\n* *Packet type*: I9\n** ANVIL Packet:\n*** I9 Standalone - Scurich: [https://app.useanvil.com/org/ganaz/w/i9-standalone-scurich/edit/preview?web=2CPGcZQKIRQg3JVhxqzq&doc=3e7c53c0-3335-11ea-92e1-f5f0e11b5e89|https://app.useanvil.com/org/ganaz/w/i9-standalone-scurich/edit/preview?web=2CPGcZQKIRQg3JVhxqzq&doc=3e7c53c0-3335-11ea-92e1-f5f0e11b5e89|smart-link] \n*** {color:#ff5630}*Allocate this packets at the bottom of the list*{color}\u00a0\n\n{panel:bgColor=#deebff}\nLink to similar [Ticket|https://ganaz.atlassian.net/browse/GAN-5462?atlOrigin=eyJpIjoiOGZiODA0ODY1ZjQ3NDdmM2E4Y2JiNzYwMzMyMjBjZmUiLCJwIjoiaiJ9] (i9 Standalone)\n{panel}\n\n\n\nIf you have questions, please reach me.", "customfield_10130": null, "customfield_10131": "the problem directly affected a legal document, so it is a high priority.", "customfield_10010": null, "customfield_10132": null, "customfield_10133": null, "customfield_10134": [{"self": "https://ganaz.atlassian.net/rest/api/2/customFieldOption/10430", "value": "Scurich Berry Farms", "id": "10430"}], "customfield_10135": null, "customfield_10014": null, "timetracking": {}, "customfield_10136": null, "customfield_10015": null, "customfield_10126": null, "customfield_10005": null, "customfield_10006": null, "customfield_10007": null, "security": null, "customfield_10008": null, "customfield_10129": null, "attachment": [], "customfield_10009": null, "summary": "Scurich Berry Farms #58 - I9 Standalone", "customfield_10120": null, "customfield_10121": [], "customfield_10000": "{}", "customfield_10001": null, "customfield_10122": null, "customfield_10002": null, "customfield_10124": null, "customfield_10003": null, "customfield_10004": null, "customfield_10125": null, "environment": null, "customfield_10119": null, "duedate": "2023-06-02", "comment": {"comments": [{"self": "https://ganaz.atlassian.net/rest/api/2/issue/17450/comment/24916", "id": "24916", "author": {"self": "https://ganaz.atlassian.net/rest/api/2/user?accountId=62780ad493111000689ece08", "accountId": "62780ad493111000689ece08", "emailAddress": "daniel.s@ganaz.com", "avatarUrls": {"48x48": "https://secure.gravatar.com/avatar/6c67edf746841016d29f333698b7f211?d=https%3A%2F%2Favatar-management--avatars.us-west-2.prod.public.atl-paas.net%2Finitials%2FDS-5.png", "24x24": "https://secure.gravatar.com/avatar/6c67edf746841016d29f333698b7f211?d=https%3A%2F%2Favatar-management--avatars.us-west-2.prod.public.atl-paas.net%2Finitials%2FDS-5.png", "16x16": "https://secure.gravatar.com/avatar/6c67edf746841016d29f333698b7f211?d=https%3A%2F%2Favatar-management--avatars.us-west-2.prod.public.atl-paas.net%2Finitials%2FDS-5.png", "32x32": "https://secure.gravatar.com/avatar/6c67edf746841016d29f333698b7f211?d=https%3A%2F%2Favatar-management--avatars.us-west-2.prod.public.atl-paas.net%2Finitials%2FDS-5.png"}, "displayName": "Daniel Schatz-Miller", "active": true, "timeZone": "America/Los_Angeles", "accountType": "atlassian"}, "body": "[~accountid:618d80f4abad3c0071fae24e] please verify (/) ", "updateAuthor": {"self": "https://ganaz.atlassian.net/rest/api/2/user?accountId=62780ad493111000689ece08", "accountId": "62780ad493111000689ece08", "emailAddress": "daniel.s@ganaz.com", "avatarUrls": {"48x48": "https://secure.gravatar.com/avatar/6c67edf746841016d29f333698b7f211?d=https%3A%2F%2Favatar-management--avatars.us-west-2.prod.public.atl-paas.net%2Finitials%2FDS-5.png", "24x24": "https://secure.gravatar.com/avatar/6c67edf746841016d29f333698b7f211?d=https%3A%2F%2Favatar-management--avatars.us-west-2.prod.public.atl-paas.net%2Finitials%2FDS-5.png", "16x16": "https://secure.gravatar.com/avatar/6c67edf746841016d29f333698b7f211?d=https%3A%2F%2Favatar-management--avatars.us-west-2.prod.public.atl-paas.net%2Finitials%2FDS-5.png", "32x32": "https://secure.gravatar.com/avatar/6c67edf746841016d29f333698b7f211?d=https%3A%2F%2Favatar-management--avatars.us-west-2.prod.public.atl-paas.net%2Finitials%2FDS-5.png"}, "displayName": "Daniel Schatz-Miller", "active": true, "timeZone": "America/Los_Angeles", "accountType": "atlassian"}, "created": "2023-06-02T06:57:43.693-0700", "updated": "2023-06-02T06:57:43.693-0700", "jsdPublic": true}, {"self": "https://ganaz.atlassian.net/rest/api/2/issue/17450/comment/24980", "id": "24980", "author": {"self": "https://ganaz.atlassian.net/rest/api/2/user?accountId=613e6eaa1238e8007108f513", "accountId": "613e6eaa1238e8007108f513", "emailAddress": "kjell@ganaz.com", "avatarUrls": {"48x48": "https://secure.gravatar.com/avatar/339f4dbb6014520e051050dc4711fbc9?d=https%3A%2F%2Favatar-management--avatars.us-west-2.prod.public.atl-paas.net%2Finitials%2FKH-0.png", "24x24": "https://secure.gravatar.com/avatar/339f4dbb6014520e051050dc4711fbc9?d=https%3A%2F%2Favatar-management--avatars.us-west-2.prod.public.atl-paas.net%2Finitials%2FKH-0.png", "16x16": "https://secure.gravatar.com/avatar/339f4dbb6014520e051050dc4711fbc9?d=https%3A%2F%2Favatar-management--avatars.us-west-2.prod.public.atl-paas.net%2Finitials%2FKH-0.png", "32x32": "https://secure.gravatar.com/avatar/339f4dbb6014520e051050dc4711fbc9?d=https%3A%2F%2Favatar-management--avatars.us-west-2.prod.public.atl-paas.net%2Finitials%2FKH-0.png"}, "displayName": "Kjell Hedstrom", "active": true, "timeZone": "US/Mountain", "accountType": "atlassian"}, "body": "[~accountid:618d80f4abad3c0071fae24e]  please let us know when you have verified this ", "updateAuthor": {"self": "https://ganaz.atlassian.net/rest/api/2/user?accountId=613e6eaa1238e8007108f513", "accountId": "613e6eaa1238e8007108f513", "emailAddress": "kjell@ganaz.com", "avatarUrls": {"48x48": "https://secure.gravatar.com/avatar/339f4dbb6014520e051050dc4711fbc9?d=https%3A%2F%2Favatar-management--avatars.us-west-2.prod.public.atl-paas.net%2Finitials%2FKH-0.png", "24x24": "https://secure.gravatar.com/avatar/339f4dbb6014520e051050dc4711fbc9?d=https%3A%2F%2Favatar-management--avatars.us-west-2.prod.public.atl-paas.net%2Finitials%2FKH-0.png", "16x16": "https://secure.gravatar.com/avatar/339f4dbb6014520e051050dc4711fbc9?d=https%3A%2F%2Favatar-management--avatars.us-west-2.prod.public.atl-paas.net%2Finitials%2FKH-0.png", "32x32": "https://secure.gravatar.com/avatar/339f4dbb6014520e051050dc4711fbc9?d=https%3A%2F%2Favatar-management--avatars.us-west-2.prod.public.atl-paas.net%2Finitials%2FKH-0.png"}, "displayName": "Kjell Hedstrom", "active": true, "timeZone": "US/Mountain", "accountType": "atlassian"}, "created": "2023-06-05T08:58:31.079-0700", "updated": "2023-06-05T08:58:31.079-0700", "jsdPublic": true}, {"self": "https://ganaz.atlassian.net/rest/api/2/issue/17450/comment/25018", "id": "25018", "author": {"self": "https://ganaz.atlassian.net/rest/api/2/user?accountId=618d80f4abad3c0071fae24e", "accountId": "618d80f4abad3c0071fae24e", "emailAddress": "osmar.e@ganaz.com", "avatarUrls": {"48x48": "https://avatar-management--avatars.us-west-2.prod.public.atl-paas.net/618d80f4abad3c0071fae24e/bc69d2f8-4938-4a4e-8407-84feff5db86f/48", "24x24": "https://avatar-management--avatars.us-west-2.prod.public.atl-paas.net/618d80f4abad3c0071fae24e/bc69d2f8-4938-4a4e-8407-84feff5db86f/24", "16x16": "https://avatar-management--avatars.us-west-2.prod.public.atl-paas.net/618d80f4abad3c0071fae24e/bc69d2f8-4938-4a4e-8407-84feff5db86f/16", "32x32": "https://avatar-management--avatars.us-west-2.prod.public.atl-paas.net/618d80f4abad3c0071fae24e/bc69d2f8-4938-4a4e-8407-84feff5db86f/32"}, "displayName": "Osmar Especiano Jimenez", "active": true, "timeZone": "America/Los_Angeles", "accountType": "atlassian"}, "body": "I was waiting to see if we needed anything else, but we will not. Everything (on the connection side is working fine).\n\nYou can close the ticket, thank you. [~accountid:62780ad493111000689ece08] [~accountid:613e6eaa1238e8007108f513] ", "updateAuthor": {"self": "https://ganaz.atlassian.net/rest/api/2/user?accountId=618d80f4abad3c0071fae24e", "accountId": "618d80f4abad3c0071fae24e", "emailAddress": "osmar.e@ganaz.com", "avatarUrls": {"48x48": "https://avatar-management--avatars.us-west-2.prod.public.atl-paas.net/618d80f4abad3c0071fae24e/bc69d2f8-4938-4a4e-8407-84feff5db86f/48", "24x24": "https://avatar-management--avatars.us-west-2.prod.public.atl-paas.net/618d80f4abad3c0071fae24e/bc69d2f8-4938-4a4e-8407-84feff5db86f/24", "16x16": "https://avatar-management--avatars.us-west-2.prod.public.atl-paas.net/618d80f4abad3c0071fae24e/bc69d2f8-4938-4a4e-8407-84feff5db86f/16", "32x32": "https://avatar-management--avatars.us-west-2.prod.public.atl-paas.net/618d80f4abad3c0071fae24e/bc69d2f8-4938-4a4e-8407-84feff5db86f/32"}, "displayName": "Osmar Especiano Jimenez", "active": true, "timeZone": "America/Los_Angeles", "accountType": "atlassian"}, "created": "2023-06-06T11:33:47.877-0700", "updated": "2023-06-06T11:33:47.877-0700", "jsdPublic": true}], "self": "https://ganaz.atlassian.net/rest/api/2/issue/17450/comment", "maxResults": 3, "total": 3, "startAt": 0}}}]